nalogovich/__init__.py
nalogovich/enums.py
nalogovich/exeptions.py
nalogovich/lknpd.py
nalogovich/py.typed
nalogovich/models/__init__.py
nalogovich/models/operations.py
nalogovich/utils/__init__.py
nalogovich/utils/checks.py
nalogovich/utils/formatters.py
nalogovich/utils/validators.py
nalogovich-1.0.5.dist-info/METADATA
nalogovich-1.0.5.dist-info/WHEEL
nalogovich-1.0.5.dist-info/licenses/LICENSE
nalogovich-1.0.5.dist-info/RECORD
