Metadata-Version: 2.4
Name: nalogovich
Version: 1.0.5
Summary: Wrapper for integration with the 'Мой налог' API service
Author-email: Ramedon <info@ramed.one>
License-File: LICENSE
Classifier: Development Status :: 4 - Beta
Classifier: Intended Audience :: Developers
Classifier: License :: OSI Approved :: MIT License
Classifier: Operating System :: OS Independent
Classifier: Programming Language :: Python :: 3
Classifier: Programming Language :: Python :: 3.8
Classifier: Programming Language :: Python :: 3.9
Classifier: Programming Language :: Python :: 3.10
Classifier: Programming Language :: Python :: 3.11
Classifier: Programming Language :: Python :: 3.12
Classifier: Programming Language :: Python :: 3.13
Requires-Python: >=3.8
Requires-Dist: aiohttp>=3.9.0
Requires-Dist: pydantic>=2.4.1
Requires-Dist: python-dateutil>=2.9.0.post0
Provides-Extra: docs
Requires-Dist: mkdocs-material; extra == 'docs'
Requires-Dist: mkdocstrings[python]; extra == 'docs'
Requires-Dist: ruff>=0.1.0; extra == 'docs'
